git_flow_wrapper/__init__.py
git_flow_wrapper/cli.py
git_flow_wrapper/git_commands.py
git_flow_wrapper-0.1.3.dist-info/entry_points.txt
git_flow_wrapper-0.1.3.dist-info/WHEEL
git_flow_wrapper-0.1.3.dist-info/METADATA
git_flow_wrapper-0.1.3.dist-info/RECORD
