Metadata-Version: 2.1
Name: git-flow-wrapper
Version: 0.1.3
Summary: Wrapper to run common git flow commands with remote repositories
License: MIT
Author: Patrick
Author-email: patrick.pwall@gmail.com
Requires-Python: >=3.6
Classifier: License :: OSI Approved :: MIT License
Classifier: Programming Language :: Python :: 3
Classifier: Programming Language :: Python :: 3.6
Classifier: Programming Language :: Python :: 3.7
Classifier: Programming Language :: Python :: 3.8
Requires-Dist: typer (>=0.1.0,<0.2.0)
